rock_finance/__init__.py
rock_finance/nasdaq.py
rock_finance/utils.py
rock_finance/version.py
rock_finance-0.0.1.dist-info/LICENSE
rock_finance-0.0.1.dist-info/METADATA
rock_finance-0.0.1.dist-info/WHEEL
rock_finance-0.0.1.dist-info/top_level.txt
rock_finance-0.0.1.dist-info/RECORD
