Metadata-Version: 2.1
Name: rock-finance
Version: 0.0.1
Summary: Rockflow Finance data downloader
Home-page: https://github.com/day253/rock-finance
Author: Junkai Dai
Author-email: daijunkai@flowcapai.com
License: UNKNOWN
Keywords: pandas,finance,pandas datareader
Platform: any
License-File: LICENSE
Requires-Dist: pandas
Requires-Dist: requests
